{
  "drivers": [
    {
      "driver_id": 400001,
      "policy_id": 200001,
      "vehicle_id": 300001,
      "vin": "1G1RC6E45F0123451",
      "driver_name": "Sarah Chen",
      "vehicle_make": "Chevrolet",
      "vehicle_model": "Equinox",
      "vehicle_year": 2023,
      "license_plate": "GA-1001",
      "base_latitude": 33.7701,
      "base_longitude": -84.3876,
      "preferred_route": "peachtree_south"
    },
    {
      "driver_id": 400002,
      "policy_id": 200002,
      "vehicle_id": 300002,
      "vin": "JN8AZ2CP9G0123452",
      "driver_name": "Emily Carter",
      "vehicle_make": "Nissan",
      "vehicle_model": "Rogue",
      "vehicle_year": 2022,
      "license_plate": "GA-1002",
      "base_latitude": 33.7490,
      "base_longitude": -84.3880,
      "preferred_route": "downtown_connector"
    },
    {
      "driver_id": 400003,
      "policy_id": 200003,
      "vehicle_id": 300003,
      "vin": "5YJSA1E2XLH987653",
      "driver_name": "Benjamin Rivera",
      "vehicle_make": "Tesla",
      "vehicle_model": "Model 3",
      "vehicle_year": 2023,
      "license_plate": "GA-1003",
      "base_latitude": 33.7550,
      "base_longitude": -84.3900,
      "preferred_route": "cumming_to_airport"
    },
    {
      "driver_id": 400004,
      "policy_id": 200004,
      "vehicle_id": 300004,
      "vin": "WA1VBFGE3L0123454",
      "driver_name": "Michael Harris",
      "vehicle_make": "Audi",
      "vehicle_model": "Q5",
      "vehicle_year": 2021,
      "license_plate": "GA-1004",
      "base_latitude": 33.7600,
      "base_longitude": -84.3850,
      "preferred_route": "peachtree_south"
    },
    {
      "driver_id": 400006,
      "policy_id": 200005,
      "vehicle_id": 300006,
      "vin": "1FMCU0KH1M0123456",
      "driver_name": "David Lee",
      "vehicle_make": "Ford",
      "vehicle_model": "Explorer",
      "vehicle_year": 2022,
      "license_plate": "GA-1005",
      "base_latitude": 33.7650,
      "base_longitude": -84.3920,
      "preferred_route": "downtown_connector"
    },
    {
      "driver_id": 400007,
      "policy_id": 200006,
      "vehicle_id": 300007,
      "vin": "3FA6P0SU2N0123457",
      "driver_name": "Jessica Thompson",
      "vehicle_make": "Ford",
      "vehicle_model": "F-150",
      "vehicle_year": 2023,
      "license_plate": "GA-1006",
      "base_latitude": 33.7720,
      "base_longitude": -84.3800,
      "preferred_route": "cumming_to_airport"
    },
    {
      "driver_id": 400008,
      "policy_id": 200007,
      "vehicle_id": 300008,
      "vin": "4T1B61HK5P0123458",
      "driver_name": "Andrew Martinez",
      "vehicle_make": "Toyota",
      "vehicle_model": "Camry",
      "vehicle_year": 2023,
      "license_plate": "GA-1007",
      "base_latitude": 33.7480,
      "base_longitude": -84.3950,
      "preferred_route": "peachtree_south"
    },
    {
      "driver_id": 400009,
      "policy_id": 200008,
      "vehicle_id": 300009,
      "vin": "1HGCP2F53N0123459",
      "driver_name": "Ashley Wilson",
      "vehicle_make": "Honda",
      "vehicle_model": "CR-V",
      "vehicle_year": 2023,
      "license_plate": "GA-1008",
      "base_latitude": 33.7580,
      "base_longitude": -84.3780,
      "preferred_route": "downtown_connector"
    },
    {
      "driver_id": 400010,
      "policy_id": 200009,
      "vehicle_id": 300010,
      "vin": "KNDP34AC6P0123460",
      "driver_name": "Christopher Garcia",
      "vehicle_make": "Kia",
      "vehicle_model": "Telluride",
      "vehicle_year": 2023,
      "license_plate": "GA-1009",
      "base_latitude": 33.7620,
      "base_longitude": -84.3820,
      "preferred_route": "cumming_to_airport"
    },
    {
      "driver_id": 400011,
      "policy_id": 200010,
      "vehicle_id": 300011,
      "vin": "5NPE24AB5P0123461",
      "driver_name": "Amanda Rodriguez",
      "vehicle_make": "Hyundai",
      "vehicle_model": "Palisade",
      "vehicle_year": 2023,
      "license_plate": "GA-1010",
      "base_latitude": 33.7530,
      "base_longitude": -84.3860,
      "preferred_route": "peachtree_south"
    },
    {
      "driver_id": 400013,
      "policy_id": 200011,
      "vehicle_id": 300013,
      "vin": "1C4RJFAG9P0123463",
      "driver_name": "Daniel Johnson",
      "vehicle_make": "Jeep",
      "vehicle_model": "Grand Cherokee",
      "vehicle_year": 2023,
      "license_plate": "GA-1011",
      "base_latitude": 33.7709,
      "base_longitude": -84.3922,
      "preferred_route": "north_ave_corridor"
    },
    {
      "driver_id": 400014,
      "policy_id": 200012,
      "vehicle_id": 300014,
      "vin": "WBA33AG01P0123464",
      "driver_name": "Lauren Brown",
      "vehicle_make": "BMW",
      "vehicle_model": "X5",
      "vehicle_year": 2022,
      "license_plate": "GA-1012",
      "base_latitude": 33.7441,
      "base_longitude": -84.4001,
      "preferred_route": "ponce_de_leon"
    },
    {
      "driver_id": 400015,
      "policy_id": 200013,
      "vehicle_id": 300015,
      "vin": "JM1KF2F35P0123465",
      "driver_name": "Matthew Davis",
      "vehicle_make": "Mazda",
      "vehicle_model": "CX-5",
      "vehicle_year": 2023,
      "license_plate": "GA-1013",
      "base_latitude": 33.7512,
      "base_longitude": -84.3749,
      "preferred_route": "ga400_north"
    },
    {
      "driver_id": 400016,
      "policy_id": 200014,
      "vehicle_id": 300016,
      "vin": "JTDKARFH6P0123466",
      "driver_name": "Stephanie Miller",
      "vehicle_make": "Lexus",
      "vehicle_model": "RX 350",
      "vehicle_year": 2023,
      "license_plate": "GA-1014",
      "base_latitude": 33.7465,
      "base_longitude": -84.3698,
      "preferred_route": "peachtree_south"
    },
    {
      "driver_id": 400017,
      "policy_id": 200015,
      "vehicle_id": 300017,
      "vin": "4S3BN7AN2P0123467",
      "driver_name": "Ryan Anderson",
      "vehicle_make": "Subaru",
      "vehicle_model": "Outback",
      "vehicle_year": 2023,
      "license_plate": "GA-1015",
      "base_latitude": 33.7411,
      "base_longitude": -84.4012,
      "preferred_route": "downtown_connector"
    }
  ]
}
