{
  "name": "ashley_wilson_base_to_work___alpharetta_tech",
  "description": "Ashley Wilson: Base \u2192 Work___Alpharetta_Tech",
  "start_location": "34.0289, -84.1986",
  "end_location": "34.06, -84.27",
  "waypoints": [
    {
      "latitude": 34.0289,
      "longitude": -84.1986,
      "street_name": "Residential Driveway",
      "speed_limit": 15,
      "has_traffic_light": false,
      "traffic_control": "none"
    },
    {
      "latitude": 34.029697,
      "longitude": -84.200431,
      "street_name": "Perimeter Center West",
      "speed_limit": 25,
      "has_traffic_light": false,
      "traffic_control": "none"
    },
    {
      "latitude": 34.030496,
      "longitude": -84.202261,
      "street_name": "Dallas Highway",
      "speed_limit": 55,
      "has_traffic_light": false,
      "traffic_control": "none"
    },
    {
      "latitude": 34.031293,
      "longitude": -84.204093,
      "street_name": "Greenwood Avenue",
      "speed_limit": 35,
      "has_traffic_light": false,
      "traffic_control": "none"
    },
    {
      "latitude": 34.03209,
      "longitude": -84.205923,
      "street_name": "Ponce de Leon Avenue",
      "speed_limit": 35,
      "has_traffic_light": false,
      "traffic_control": "none"
    },
    {
      "latitude": 34.032888,
      "longitude": -84.207754,
      "street_name": "Powers Ferry Road",
      "speed_limit": 35,
      "has_traffic_light": true,
      "traffic_control": "traffic_light"
    },
    {
      "latitude": 34.033685,
      "longitude": -84.209584,
      "street_name": "Candler Road",
      "speed_limit": 35,
      "has_traffic_light": false,
      "traffic_control": "none"
    },
    {
      "latitude": 34.034482,
      "longitude": -84.211416,
      "street_name": "Moreland Avenue",
      "speed_limit": 35,
      "has_traffic_light": false,
      "traffic_control": "yield"
    },
    {
      "latitude": 34.03528,
      "longitude": -84.213247,
      "street_name": "Scott Boulevard",
      "speed_limit": 45,
      "has_traffic_light": false,
      "traffic_control": "none"
    },
    {
      "latitude": 34.036077,
      "longitude": -84.215077,
      "street_name": "Peachtree Street NW",
      "speed_limit": 35,
      "has_traffic_light": false,
      "traffic_control": "none"
    },
    {
      "latitude": 34.036874,
      "longitude": -84.216908,
      "street_name": "Windward Parkway",
      "speed_limit": 45,
      "has_traffic_light": false,
      "traffic_control": "none"
    },
    {
      "latitude": 34.037672,
      "longitude": -84.218738,
      "street_name": "Broadland Road",
      "speed_limit": 45,
      "has_traffic_light": false,
      "traffic_control": "none"
    },
    {
      "latitude": 34.038469,
      "longitude": -84.220569,
      "street_name": "Northside Drive",
      "speed_limit": 45,
      "has_traffic_light": true,
      "traffic_control": "traffic_light"
    },
    {
      "latitude": 34.039267,
      "longitude": -84.222399,
      "street_name": "McFarland Parkway",
      "speed_limit": 45,
      "has_traffic_light": false,
      "traffic_control": "none"
    },
    {
      "latitude": 34.040064,
      "longitude": -84.224231,
      "street_name": "Clifton Road",
      "speed_limit": 45,
      "has_traffic_light": false,
      "traffic_control": "none"
    },
    {
      "latitude": 34.040861,
      "longitude": -84.226061,
      "street_name": "Cumming City Beach Road",
      "speed_limit": 45,
      "has_traffic_light": false,
      "traffic_control": "none"
    },
    {
      "latitude": 34.041659,
      "longitude": -84.227892,
      "street_name": "Clifton Road",
      "speed_limit": 45,
      "has_traffic_light": true,
      "traffic_control": "traffic_light"
    },
    {
      "latitude": 34.042456,
      "longitude": -84.229723,
      "street_name": "GA-400 South",
      "speed_limit": 55,
      "has_traffic_light": false,
      "traffic_control": "none"
    },
    {
      "latitude": 34.043255,
      "longitude": -84.231554,
      "street_name": "12th Street",
      "speed_limit": 35,
      "has_traffic_light": false,
      "traffic_control": "none"
    },
    {
      "latitude": 34.044051,
      "longitude": -84.233384,
      "street_name": "Clairmont Road",
      "speed_limit": 45,
      "has_traffic_light": false,
      "traffic_control": "none"
    },
    {
      "latitude": 34.044848,
      "longitude": -84.235215,
      "street_name": "Beverly Road",
      "speed_limit": 45,
      "has_traffic_light": true,
      "traffic_control": "traffic_light"
    },
    {
      "latitude": 34.045647,
      "longitude": -84.237045,
      "street_name": "Broadland Road",
      "speed_limit": 45,
      "has_traffic_light": false,
      "traffic_control": "none"
    },
    {
      "latitude": 34.046443,
      "longitude": -84.238877,
      "street_name": "Clifton Road",
      "speed_limit": 45,
      "has_traffic_light": false,
      "traffic_control": "none"
    },
    {
      "latitude": 34.047242,
      "longitude": -84.240707,
      "street_name": "Crossville Road",
      "speed_limit": 45,
      "has_traffic_light": false,
      "traffic_control": "none"
    },
    {
      "latitude": 34.048038,
      "longitude": -84.242538,
      "street_name": "14th Street",
      "speed_limit": 35,
      "has_traffic_light": true,
      "traffic_control": "traffic_light"
    },
    {
      "latitude": 34.048835,
      "longitude": -84.24437,
      "street_name": "16th Street",
      "speed_limit": 35,
      "has_traffic_light": false,
      "traffic_control": "none"
    },
    {
      "latitude": 34.049634,
      "longitude": -84.246199,
      "street_name": "Lower Roswell Road",
      "speed_limit": 45,
      "has_traffic_light": false,
      "traffic_control": "none"
    },
    {
      "latitude": 34.050431,
      "longitude": -84.24803,
      "street_name": "LaVista Road",
      "speed_limit": 45,
      "has_traffic_light": false,
      "traffic_control": "none"
    },
    {
      "latitude": 34.051229,
      "longitude": -84.249861,
      "street_name": "Johnson Ferry Road",
      "speed_limit": 45,
      "has_traffic_light": true,
      "traffic_control": "traffic_light"
    },
    {
      "latitude": 34.052025,
      "longitude": -84.251693,
      "street_name": "Glen Iris Drive",
      "speed_limit": 45,
      "has_traffic_light": false,
      "traffic_control": "none"
    },
    {
      "latitude": 34.052823,
      "longitude": -84.253523,
      "street_name": "Lakeshore Drive",
      "speed_limit": 45,
      "has_traffic_light": false,
      "traffic_control": "none"
    },
    {
      "latitude": 34.053621,
      "longitude": -84.255353,
      "street_name": "Union Hill Road",
      "speed_limit": 45,
      "has_traffic_light": false,
      "traffic_control": "none"
    },
    {
      "latitude": 34.054419,
      "longitude": -84.257184,
      "street_name": "Sawnee Avenue",
      "speed_limit": 35,
      "has_traffic_light": false,
      "traffic_control": "none"
    },
    {
      "latitude": 34.055216,
      "longitude": -84.259016,
      "street_name": "Glenwood Avenue",
      "speed_limit": 35,
      "has_traffic_light": false,
      "traffic_control": "none"
    },
    {
      "latitude": 34.056013,
      "longitude": -84.260846,
      "street_name": "Clifton Road",
      "speed_limit": 35,
      "has_traffic_light": false,
      "traffic_control": "none"
    },
    {
      "latitude": 34.05681,
      "longitude": -84.262677,
      "street_name": "I-85 North",
      "speed_limit": 70,
      "has_traffic_light": false,
      "traffic_control": "none"
    },
    {
      "latitude": 34.057607,
      "longitude": -84.264507,
      "street_name": "9th Street",
      "speed_limit": 35,
      "has_traffic_light": false,
      "traffic_control": "none"
    },
    {
      "latitude": 34.058405,
      "longitude": -84.266338,
      "street_name": "Habersham Road",
      "speed_limit": 25,
      "has_traffic_light": false,
      "traffic_control": "none"
    },
    {
      "latitude": 34.059203,
      "longitude": -84.268169,
      "street_name": "Freedom Parkway",
      "speed_limit": 45,
      "has_traffic_light": false,
      "traffic_control": "none"
    },
    {
      "latitude": 34.06,
      "longitude": -84.27,
      "street_name": "Destination Parking",
      "speed_limit": 15,
      "has_traffic_light": false,
      "traffic_control": "none"
    }
  ]
}