{
  "name": "jason_patel_tucker_town_center_to_stone_mountain",
  "description": "Jason Patel: Tucker_Town_Center \u2192 Stone_Mountain",
  "start_location": "33.8528, -84.208",
  "end_location": "33.812, -84.1452",
  "waypoints": [
    {
      "latitude": 33.8528,
      "longitude": -84.208,
      "street_name": "Residential Driveway",
      "speed_limit": 15,
      "has_traffic_light": false,
      "traffic_control": "none"
    },
    {
      "latitude": 33.851754,
      "longitude": -84.20639,
      "street_name": "Windy Hill Road",
      "speed_limit": 25,
      "has_traffic_light": false,
      "traffic_control": "none"
    },
    {
      "latitude": 33.850709,
      "longitude": -84.204779,
      "street_name": "Freedom Parkway",
      "speed_limit": 45,
      "has_traffic_light": false,
      "traffic_control": "none"
    },
    {
      "latitude": 33.849661,
      "longitude": -84.20317,
      "street_name": "Highway 120",
      "speed_limit": 55,
      "has_traffic_light": false,
      "traffic_control": "none"
    },
    {
      "latitude": 33.848616,
      "longitude": -84.20156,
      "street_name": "Old Milton Parkway",
      "speed_limit": 45,
      "has_traffic_light": false,
      "traffic_control": "none"
    },
    {
      "latitude": 33.84757,
      "longitude": -84.199948,
      "street_name": "Virginia Avenue",
      "speed_limit": 35,
      "has_traffic_light": true,
      "traffic_control": "traffic_light"
    },
    {
      "latitude": 33.846523,
      "longitude": -84.198338,
      "street_name": "Old Milton Parkway",
      "speed_limit": 45,
      "has_traffic_light": true,
      "traffic_control": "traffic_light"
    },
    {
      "latitude": 33.845477,
      "longitude": -84.196728,
      "street_name": "Edgewood Avenue",
      "speed_limit": 35,
      "has_traffic_light": false,
      "traffic_control": "yield"
    },
    {
      "latitude": 33.844431,
      "longitude": -84.195119,
      "street_name": "Northside Drive",
      "speed_limit": 45,
      "has_traffic_light": true,
      "traffic_control": "traffic_light"
    },
    {
      "latitude": 33.843384,
      "longitude": -84.193508,
      "street_name": "Peachtree Battle Avenue",
      "speed_limit": 45,
      "has_traffic_light": false,
      "traffic_control": "none"
    },
    {
      "latitude": 33.842338,
      "longitude": -84.191898,
      "street_name": "Cheshire Bridge Road",
      "speed_limit": 45,
      "has_traffic_light": false,
      "traffic_control": "none"
    },
    {
      "latitude": 33.841293,
      "longitude": -84.190288,
      "street_name": "Tuxedo Road",
      "speed_limit": 45,
      "has_traffic_light": false,
      "traffic_control": "none"
    },
    {
      "latitude": 33.840246,
      "longitude": -84.188677,
      "street_name": "Cypress Street",
      "speed_limit": 35,
      "has_traffic_light": true,
      "traffic_control": "traffic_light"
    },
    {
      "latitude": 33.839199,
      "longitude": -84.187068,
      "street_name": "Pine Street",
      "speed_limit": 35,
      "has_traffic_light": false,
      "traffic_control": "none"
    },
    {
      "latitude": 33.838153,
      "longitude": -84.185457,
      "street_name": "Highway 42",
      "speed_limit": 55,
      "has_traffic_light": false,
      "traffic_control": "none"
    },
    {
      "latitude": 33.837109,
      "longitude": -84.183846,
      "street_name": "19th Street",
      "speed_limit": 35,
      "has_traffic_light": false,
      "traffic_control": "none"
    },
    {
      "latitude": 33.836062,
      "longitude": -84.182236,
      "street_name": "Glen Iris Drive",
      "speed_limit": 45,
      "has_traffic_light": true,
      "traffic_control": "traffic_light"
    },
    {
      "latitude": 33.835015,
      "longitude": -84.180625,
      "street_name": "Penn Avenue",
      "speed_limit": 45,
      "has_traffic_light": false,
      "traffic_control": "none"
    },
    {
      "latitude": 33.833968,
      "longitude": -84.179016,
      "street_name": "Druid Hills Road",
      "speed_limit": 45,
      "has_traffic_light": false,
      "traffic_control": "none"
    },
    {
      "latitude": 33.832924,
      "longitude": -84.177406,
      "street_name": "Stone Mountain Freeway",
      "speed_limit": 45,
      "has_traffic_light": false,
      "traffic_control": "none"
    },
    {
      "latitude": 33.831878,
      "longitude": -84.175795,
      "street_name": "Atlanta Highway",
      "speed_limit": 55,
      "has_traffic_light": false,
      "traffic_control": "none"
    },
    {
      "latitude": 33.830832,
      "longitude": -84.174185,
      "street_name": "Briarcliff Road",
      "speed_limit": 45,
      "has_traffic_light": false,
      "traffic_control": "none"
    },
    {
      "latitude": 33.829785,
      "longitude": -84.172574,
      "street_name": "Austell Road",
      "speed_limit": 45,
      "has_traffic_light": false,
      "traffic_control": "none"
    },
    {
      "latitude": 33.828739,
      "longitude": -84.170963,
      "street_name": "North Highland Avenue",
      "speed_limit": 45,
      "has_traffic_light": false,
      "traffic_control": "none"
    },
    {
      "latitude": 33.827693,
      "longitude": -84.169354,
      "street_name": "Pine Street",
      "speed_limit": 35,
      "has_traffic_light": true,
      "traffic_control": "traffic_light"
    },
    {
      "latitude": 33.826647,
      "longitude": -84.167745,
      "street_name": "I-75 South",
      "speed_limit": 70,
      "has_traffic_light": false,
      "traffic_control": "none"
    },
    {
      "latitude": 33.8256,
      "longitude": -84.166134,
      "street_name": "I-75 South",
      "speed_limit": 70,
      "has_traffic_light": false,
      "traffic_control": "none"
    },
    {
      "latitude": 33.824554,
      "longitude": -84.164523,
      "street_name": "Duluth Highway",
      "speed_limit": 55,
      "has_traffic_light": false,
      "traffic_control": "none"
    },
    {
      "latitude": 33.823508,
      "longitude": -84.162913,
      "street_name": "Broadland Road",
      "speed_limit": 45,
      "has_traffic_light": true,
      "traffic_control": "traffic_light"
    },
    {
      "latitude": 33.822462,
      "longitude": -84.161303,
      "street_name": "Moreland Avenue",
      "speed_limit": 45,
      "has_traffic_light": false,
      "traffic_control": "none"
    },
    {
      "latitude": 33.821416,
      "longitude": -84.159693,
      "street_name": "Collier Road",
      "speed_limit": 45,
      "has_traffic_light": false,
      "traffic_control": "none"
    },
    {
      "latitude": 33.820368,
      "longitude": -84.158081,
      "street_name": "Union Hill Road",
      "speed_limit": 45,
      "has_traffic_light": false,
      "traffic_control": "none"
    },
    {
      "latitude": 33.819324,
      "longitude": -84.156472,
      "street_name": "Peachtree Industrial Blvd",
      "speed_limit": 35,
      "has_traffic_light": false,
      "traffic_control": "none"
    },
    {
      "latitude": 33.818276,
      "longitude": -84.154862,
      "street_name": "Argonne Avenue",
      "speed_limit": 35,
      "has_traffic_light": false,
      "traffic_control": "none"
    },
    {
      "latitude": 33.817231,
      "longitude": -84.15325,
      "street_name": "Scott Boulevard",
      "speed_limit": 45,
      "has_traffic_light": false,
      "traffic_control": "none"
    },
    {
      "latitude": 33.816184,
      "longitude": -84.151642,
      "street_name": "Edgewood Avenue",
      "speed_limit": 35,
      "has_traffic_light": true,
      "traffic_control": "traffic_light"
    },
    {
      "latitude": 33.815138,
      "longitude": -84.15003,
      "street_name": "I-20 East",
      "speed_limit": 70,
      "has_traffic_light": false,
      "traffic_control": "none"
    },
    {
      "latitude": 33.814093,
      "longitude": -84.148421,
      "street_name": "12th Street",
      "speed_limit": 25,
      "has_traffic_light": false,
      "traffic_control": "none"
    },
    {
      "latitude": 33.813045,
      "longitude": -84.14681,
      "street_name": "I-985 North",
      "speed_limit": 70,
      "has_traffic_light": false,
      "traffic_control": "none"
    },
    {
      "latitude": 33.812,
      "longitude": -84.1452,
      "street_name": "Destination Parking",
      "speed_limit": 15,
      "has_traffic_light": false,
      "traffic_control": "none"
    }
  ]
}